unitgrade/__init__.py
unitgrade/artifacts.py
unitgrade/evaluate.py
unitgrade/framework.py
unitgrade/pupdb.py
unitgrade/runners.py
unitgrade/utils.py
unitgrade/version.py
unitgrade/dashboard/__init__.py
unitgrade/dashboard/app.py
unitgrade/dashboard/app_helpers.py
unitgrade/dashboard/dashboard_cli.py
unitgrade/dashboard/dbwatcher.py
unitgrade/dashboard/ephermaltransfer.py
unitgrade/dashboard/file_change_handler.py
unitgrade/dashboard/watcher.py
unitgrade/dashboard/static/favicon.ico
unitgrade/dashboard/static/sidebars.css
unitgrade/dashboard/static/sidebars.js
unitgrade/dashboard/static/unitgrade.css
unitgrade/dashboard/static/unitgrade.js
unitgrade/dashboard/static/wz_js.js
unitgrade/dashboard/static/wz_style.css
unitgrade/dashboard/static/wz_style_modified.css
unitgrade/dashboard/templates/base.html
unitgrade/dashboard/templates/bootstrap.html
unitgrade/dashboard/templates/index3.html
unitgrade/dashboard/templates/info.html
unitgrade/dashboard/templates/terminal.html
unitgrade/dashboard/templates/wz.html
unitgrade-1.0.0.11.dist-info/LICENSE
unitgrade-1.0.0.11.dist-info/METADATA
unitgrade-1.0.0.11.dist-info/WHEEL
unitgrade-1.0.0.11.dist-info/entry_points.txt
unitgrade-1.0.0.11.dist-info/top_level.txt
unitgrade-1.0.0.11.dist-info/RECORD
