Metadata-Version: 2.1
Name: unitgrade
Version: 1.0.0.11
Summary: A student homework/exam evaluation framework build on pythons unittest framework.
Home-page: https://lab.compute.dtu.dk/tuhe/unitgrade
Author: Tue Herlau
Author-email: tuhe@dtu.dk
License: MIT
Project-URL: Bug Tracker, https://lab.compute.dtu.dk/tuhe/unitgrade/issues
Classifier: Programming Language :: Python :: 3
Classifier: License :: OSI Approved :: MIT License
Classifier: Operating System :: OS Independent
Requires-Python: >=3.8
License-File: LICENSE
Requires-Dist: numpy
Requires-Dist: tabulate
Requires-Dist: pyfiglet <1.0.0
Requires-Dist: coverage
Requires-Dist: colorama
Requires-Dist: tqdm
Requires-Dist: importnb
Requires-Dist: requests
Requires-Dist: pandas
Requires-Dist: watchdog
Requires-Dist: flask-socketio
Requires-Dist: flask
Requires-Dist: Werkzeug >=2.3.0
Requires-Dist: diskcache
